Metadata-Version: 2.1
Name: odoo12-addon-brand-external-report-layout
Version: 12.0.1.0.3
Summary: This module allows you to have a different layout by brand for your external reports.
Home-page: https://github.com/OCA/brand
Author: ACSONE SA/NV,Odoo Community Association (OCA)
Author-email: support@odoo-community.org
License: AGPL-3
Platform: UNKNOWN
Classifier: Programming Language :: Python
Classifier: Framework :: Odoo
Classifier: Framework :: Odoo :: 12.0
Classifier: License :: OSI Approved :: GNU Affero General Public License v3
Requires-Python: >=3.5
Requires-Dist: odoo12-addon-brand
Requires-Dist: odoo (<12.1dev,>=12.0a)
